[
    {
        "nim": "120140194",
        "nama": "Muhammad Elang Permadani",
        "prodi": "Teknik Informatika"
    },
    {
        "nim": "120140195",
        "nama": "Doni Salaman",
        "prodi": "Teknik Informatika"
    },
    {
        "nim": "120140196",
        "nama": "Reza Pratama",
        "prodi": "Teknik Informatika"
    },
    {
        "nim": "120140197",
        "nama": "Rizky Ramadhan",
        "prodi": "Teknik Informatika"
    },
    {
        "nim": "120160198",
        "nama": "Ratu Dwi",
        "prodi": "Teknik Elektro"
    },
    {
        "nim": "120160199",
        "nama": "Reyhan Baik",
        "prodi": "Teknik Elektro"
    },
    {
        "nim": "120160200",
        "nama": "Budi Susanto",
        "prodi": "Teknik Elektro"
    },
    {
        "nim": "120160201",
        "nama": "Joko Prawi",
        "prodi": "Teknik Elektro"
    },
    {
        "nim": "120170150",
        "nama": "Pratama Agung",
        "prodi": "Teknik Sipil"
    },
    {
        "nim": "120170151",
        "nama": "Sambo Ferdian",
        "prodi": "Teknik Sipil"
    },
    {
        "nim": "120170152",
        "nama": "Reyhan Jahat",
        "prodi": "Teknik Sipil"
    },
    {
        "nim": "120170153",
        "nama": "Paun Muda",
        "prodi": "Teknik Sipil"
    }
]